strayl_lint/__init__.py
strayl_lint/checker.py
strayl_lint/cli.py
strayl_lint/scanner.py
strayl_lint-0.1.4.dist-info/licenses/LICENSE
strayl_lint-0.1.4.dist-info/METADATA
strayl_lint-0.1.4.dist-info/WHEEL
strayl_lint-0.1.4.dist-info/entry_points.txt
strayl_lint-0.1.4.dist-info/top_level.txt
strayl_lint-0.1.4.dist-info/RECORD
