Metadata-Version: 2.4
Name: strayl-lint
Version: 0.1.4
Summary: AI-powered API validation tool - never fear API updates again
Author-email: Strayl Team <support@strayl.dev>
License: MIT
Project-URL: Homepage, https://strayl.dev
Project-URL: Documentation, https://strayl.dev/docs
Project-URL: Repository, https://github.com/AlemzhanJ/strayl-lint
Keywords: api,validation,linter,ci-cd,testing
Classifier: Development Status :: 3 - Alpha
Classifier: Intended Audience :: Developers
Classifier: License :: OSI Approved :: MIT License
Classifier: Programming Language :: Python :: 3
Classifier: Programming Language :: Python :: 3.8
Classifier: Programming Language :: Python :: 3.9
Classifier: Programming Language :: Python :: 3.10
Classifier: Programming Language :: Python :: 3.11
Classifier: Programming Language :: Python :: 3.12
Requires-Python: >=3.8
License-File: LICENSE
Requires-Dist: typer>=0.9.0
Requires-Dist: requests>=2.31.0
Requires-Dist: rich>=13.0.0
Provides-Extra: dev
Requires-Dist: pytest>=7.0.0; extra == "dev"
Requires-Dist: black>=23.0.0; extra == "dev"
Requires-Dist: mypy>=1.0.0; extra == "dev"
Dynamic: license-file
